marvinbo/__init__.py
marvinbo/basics.py
marvinbo/core_cuda.cu
marvinbo/gpu_ops.py
marvinbo/lib_cuda.dll
marvinbo/math.py
marvinbo/sparse.py
marvinbo-0.1.1.dist-info/licenses/License
marvinbo-0.1.1.dist-info/METADATA
marvinbo-0.1.1.dist-info/WHEEL
marvinbo-0.1.1.dist-info/top_level.txt
marvinbo-0.1.1.dist-info/RECORD
