Metadata-Version: 2.4
Name: marvinbo
Version: 0.1.1
Summary: A sparse matrix library with CUDA acceleration.
Author-email: Marvin <202522081036@mail.bnu.edu.cn>
License: MIT
Project-URL: Homepage, https://github.com/marvinbo
Project-URL: Source, https://github.com/Seto1919810/marvinbo
Requires-Python: >=3.8
License-File: License
Requires-Dist: numpy
Dynamic: license-file
